generationkwh/__init__.py
generationkwh/amortizations.py
generationkwh/amortizations_test.py
generationkwh/dealer.py
generationkwh/dealer_test.py
generationkwh/fareperiodcurve.py
generationkwh/investmentmodel.py
generationkwh/investmentstate.py
generationkwh/investmentstate_test.py
generationkwh/isodates.py
generationkwh/memberrightscurve.py
generationkwh/memberrightscurve_test.py
generationkwh/memberrightsusage.py
generationkwh/memberrightsusage_test.py
generationkwh/productiontorightspershare.py
generationkwh/productiontorightspershare_test.py
generationkwh/rightscorrection.py
generationkwh/rightscorrection_test.py
generationkwh/rightsgranter.py
generationkwh/rightsgranter_test.py
generationkwh/rightspershare.py
generationkwh/rightspershare_test.py
generationkwh/sharescurve.py
generationkwh/sharescurve_test.py
generationkwh/testutils.py
generationkwh/usagetracker.py
generationkwh/usagetracker_test.py
som_generationkwh/__init__.py
som_generationkwh/__terp__.py
som_generationkwh/account_invoice.py
som_generationkwh/assignment.py
som_generationkwh/emission.py
som_generationkwh/erpwrapper.py
som_generationkwh/giscedata_facturacio.py
som_generationkwh/giscedata_polissa.py
som_generationkwh/holidays.py
som_generationkwh/investment.py
som_generationkwh/investment_sign.py
som_generationkwh/investment_strategy.py
som_generationkwh/remainder.py
som_generationkwh/res_partner.py
som_generationkwh/rightsgranter.py
som_generationkwh/som_generationkwh.py
som_generationkwh/somenergia_soci.py
som_generationkwh/report/__init__.py
som_generationkwh/report/report_amortization_gkwh.py
som_generationkwh/report/report_contract_apo.py
som_generationkwh/report/report_retencions_gkwh.py
som_generationkwh/report/report_webkit.py
som_generationkwh/wizard/__init__.py
som_generationkwh/wizard/wizard_aeat193_from_gkwh_invoices.py
som_generationkwh/wizard/wizard_baixa_soci.py
som_generationkwh/wizard/wizard_contract_sign_signaturit.py
somenergia_generationkwh-2.5.8.dist-info/LICENSE
somenergia_generationkwh-2.5.8.dist-info/METADATA
somenergia_generationkwh-2.5.8.dist-info/WHEEL
somenergia_generationkwh-2.5.8.dist-info/top_level.txt
somenergia_generationkwh-2.5.8.dist-info/RECORD
