Metadata-Version: 2.1
Name: somenergia-generationkwh
Version: 2.5.8
Summary: OpenERP module and library to manage Som Energia's Generation kWh
Home-page: https://github.com/Som-Energia/somenergia-generationkwh
Author: Som Energia SCCL
Author-email: info@somenergia.coop
License: GNU Affero General Public License v3 or later (AGPLv3+)
Classifier: Programming Language :: Python
Classifier: Programming Language :: Python :: 3
Classifier: Topic :: Software Development :: Libraries :: Python Modules
Classifier: Intended Audience :: Developers
Classifier: Development Status :: 2 - Pre-Alpha
Classifier: License :: OSI Approved :: GNU Affero General Public License v3 or later (AGPLv3+)
Classifier: Operating System :: OS Independent
License-File: LICENSE
Requires-Dist: setuptools >=20.4
Requires-Dist: yamlns >=0.6
Requires-Dist: tqdm
Requires-Dist: b2btest
Requires-Dist: lxml
Requires-Dist: numpy
Requires-Dist: decorator
Requires-Dist: plantmeter
Requires-Dist: python-dateutil
Requires-Dist: consolemsg >=0.3
Requires-Dist: somutils
Requires-Dist: pytest
Requires-Dist: pytest-cov
